pyOSPParser/__init__.py
pyOSPParser/logging_configuration.py
pyOSPParser/model_description.py
pyOSPParser/scenario.py
pyOSPParser/system_configuration.py
pyOSPParser/xmlschema/LoggingConfiguration.xsd
pyOSPParser/xmlschema/OspModelDescription.xsd
pyOSPParser/xmlschema/OspSystemStructure.xsd
pyOSPParser/xmlschema/fmi2unit.xsd
test/__init__.py
test/test_logging_config.py
test/test_model_description.py
test/test_scenario.py
test/test_system_configuration.py
pyOSPParser-0.5.0.dist-info/METADATA
pyOSPParser-0.5.0.dist-info/WHEEL
pyOSPParser-0.5.0.dist-info/top_level.txt
pyOSPParser-0.5.0.dist-info/RECORD
