Metadata-Version: 2.1
Name: pyOSPParser
Version: 0.5.0
Summary: A module to parse or deploy XML/JSON files for Open Simulation Platform.
Home-page: https://github.com/kevinksyTRD/pyOSPParser
License: Apache License 2.0
Project-URL: Source, https://github.com/kevinksyTRD/pyOSPParser
Project-URL: Bug Reports, https://github.com/kevinksyTRD/pyOSPParser/issues
Keywords: Open-Simulation-Platform Parser XML JSON
Classifier: Intended Audience :: Science/Research
Classifier: Topic :: Scientific/Engineering
Classifier: License :: OSI Approved :: Apache Software License
Classifier: Programming Language :: Python :: 3
Requires-Python: >=3.8
Requires-Dist: xmlschema (~=1.2.2)
